harvesttext/__init__.py
harvesttext/download_utils.py
harvesttext/ent_network.py
harvesttext/ent_retrieve.py
harvesttext/harvesttext.py
harvesttext/parsing.py
harvesttext/resources.py
harvesttext/sentiment.py
harvesttext/summary.py
harvesttext/word_discover.py
harvesttext/algorithms/__init__.py
harvesttext/algorithms/entity_discoverer.py
harvesttext/algorithms/keyword.py
harvesttext/algorithms/match_patterns.py
harvesttext/algorithms/sent_dict.py
harvesttext/algorithms/texttile.py
harvesttext/algorithms/utils.py
harvesttext/algorithms/word_discoverer.py
harvesttext/resources/LH_senti_lexicon.json
harvesttext/resources/THUOCL.json
harvesttext/resources/bd_stopwords.json
harvesttext/resources/pinyin_adjlist.json
harvesttext/resources/qh_sent_dict.json
harvesttext/resources/sanguo_docs.json
harvesttext/resources/sanguo_entity_dict.json
harvesttext-0.8.2.1.dist-info/LICENSE
harvesttext-0.8.2.1.dist-info/METADATA
harvesttext-0.8.2.1.dist-info/WHEEL
harvesttext-0.8.2.1.dist-info/top_level.txt
harvesttext-0.8.2.1.dist-info/RECORD
