Metadata-Version: 2.1
Name: harvesttext
Version: 0.8.2.1
Summary: UNKNOWN
Home-page: https://github.com/blmoistawinde/HarvestText
Author: blmoistawinde
Author-email: 1840962220@qq.com
License: MIT
Keywords: NLP,tokenizing,entity linking,sentiment analysis,text cleaning
Platform: all
Classifier: License :: OSI Approved :: MIT License
Classifier: Operating System :: OS Independent
Classifier: Natural Language :: Chinese (Simplified)
Classifier: Natural Language :: Chinese (Traditional)
Classifier: Programming Language :: Python :: 3
Classifier: Topic :: Text Processing
